degr33/__init__.py
degr33/cli.py
degr33-1.1.1.dist-info/METADATA
degr33-1.1.1.dist-info/WHEEL
degr33-1.1.1.dist-info/entry_points.txt
degr33-1.1.1.dist-info/top_level.txt
degr33-1.1.1.dist-info/RECORD
