Metadata-Version: 2.4
Name: degr33
Version: 1.1.1
Summary: Read-only Linux command explanation tool
Requires-Python: >=3.8
Requires-Dist: openai>=1.0.0
